rich_tools/__init__.py
rich_tools/table.py
rich_tools/text.py
rich_tools-0.5.1.dist-info/LICENSE
rich_tools-0.5.1.dist-info/METADATA
rich_tools-0.5.1.dist-info/WHEEL
rich_tools-0.5.1.dist-info/RECORD
