Metadata-Version: 2.1
Name: rich-tools
Version: 0.5.1
Summary: A python package with helpful tools when working with the rich python library.
Home-page: https://github.com/avi-perl/rich_tools
License: MIT
Keywords: rich,pandas
Author: Avi Perl
Author-email: avi@aviperl.me
Requires-Python: >=3.9,<4.0
Classifier: Development Status :: 4 - Beta
Classifier: Environment :: Console
Classifier: Intended Audience :: Developers
Classifier: License :: OSI Approved :: MIT License
Classifier: Operating System :: MacOS
Classifier: Operating System :: Microsoft :: Windows
Classifier: Operating System :: POSIX :: Linux
Classifier: Programming Language :: Python :: 3
Classifier: Programming Language :: Python :: 3.9
Classifier: Programming Language :: Python :: 3.10
Classifier: Programming Language :: Python :: 3.11
Classifier: Programming Language :: Python :: 3.12
Classifier: Programming Language :: Python :: 3.7
Classifier: Programming Language :: Python :: 3.8
Classifier: Typing :: Typed
Requires-Dist: pandas (>=2.2.2,<3.0.0)
Requires-Dist: rich (>=13.8.0,<14.0.0)
Project-URL: Repository, https://github.com/avi-perl/rich_tools
